kindwise/__init__.py
kindwise/core.py
kindwise/crop_health.py
kindwise/insect.py
kindwise/models.py
kindwise/mushroom.py
kindwise/plant.py
kindwise/resources/views.crop_health.crop.json
kindwise/resources/views.crop_health.disease.json
kindwise/resources/views.insect.json
kindwise/resources/views.mushroom.json
kindwise/resources/views.plant.disease.json
kindwise/resources/views.plant.json
kindwise/router.py
kindwise/settings.py
kindwise/tests/__init__.py
kindwise/tests/conftest.py
kindwise/tests/resources/images/aloe-vera.jpg
kindwise/tests/resources/images/amanita_muscaria.jpg
kindwise/tests/resources/images/bee.jpeg
kindwise/tests/resources/images/padli.png
kindwise/tests/resources/images/potato.late_blight.jpg
kindwise/tests/resources/images/wheat.jpg
kindwise/tests/test_core.py
kindwise/tests/test_crop.py
kindwise/tests/test_insect.py
kindwise/tests/test_mushroom.py
kindwise/tests/test_plant.py
kindwise/tests/test_router.py
kindwise_api_client-0.7.1.dist-info/METADATA
kindwise_api_client-0.7.1.dist-info/WHEEL
kindwise_api_client-0.7.1.dist-info/licenses/LICENSE
kindwise_api_client-0.7.1.dist-info/RECORD
