Metadata-Version: 2.4
Name: kindwise-api-client
Version: 0.7.1
Summary: Python SDK toolkit for integrating Kindwise API
License: MIT
License-File: LICENSE
Author: Simon Plhak
Author-email: simon.plhak@flowerchecker.com
Requires-Python: >=3.10,<4.0
Classifier: License :: OSI Approved :: MIT License
Classifier: Programming Language :: Python :: 3
Classifier: Programming Language :: Python :: 3.10
Classifier: Programming Language :: Python :: 3.11
Classifier: Programming Language :: Python :: 3.12
Classifier: Programming Language :: Python :: 3.13
Classifier: Programming Language :: Python :: 3.14
Provides-Extra: router
Requires-Dist: huggingface-hub (>=0.35.3,<0.36.0) ; extra == "router"
Requires-Dist: numpy (==2.2.6) ; extra == "router"
Requires-Dist: pillow
Requires-Dist: python-dotenv
Requires-Dist: requests
Requires-Dist: torch (==2.7.0) ; extra == "router"
Requires-Dist: torchvision (==0.22.0) ; extra == "router"
Project-URL: Repository, https://github.com/flowerchecker/kindwise
